hatch_kicad/__init__.py
hatch_kicad/_version.py
hatch_kicad/build.py
hatch_kicad/config.py
hatch_kicad/hooks.py
hatch_kicad/licenses/supported.py
hatch_kicad-0.3.0.dist-info/METADATA
hatch_kicad-0.3.0.dist-info/WHEEL
hatch_kicad-0.3.0.dist-info/entry_points.txt
hatch_kicad-0.3.0.dist-info/licenses/LICENSE.txt
hatch_kicad-0.3.0.dist-info/RECORD
