Metadata-Version: 2.1
Name: hatch-kicad
Version: 0.3.0
Summary: A hatch plugin for packaging KiCad plugins
Project-URL: Documentation, https://github.com/adamws/hatch-kicad#readme
Project-URL: Issues, https://github.com/adamws/hatch-kicad/issues
Project-URL: Source, https://github.com/adamws/hatch-kicad
Author-email: adamws <adamws@users.noreply.github.com>
License-Expression: MIT
License-File: LICENSE.txt
Classifier: Development Status :: 4 - Beta
Classifier: Framework :: Hatch
Classifier: Programming Language :: Python
Classifier: Programming Language :: Python :: 3.7
Classifier: Programming Language :: Python :: 3.8
Classifier: Programming Language :: Python :: 3.9
Classifier: Programming Language :: Python :: 3.10
Classifier: Programming Language :: Python :: 3.11
Classifier: Programming Language :: Python :: Implementation :: CPython
Classifier: Programming Language :: Python :: Implementation :: PyPy
Requires-Python: >=3.7
Requires-Dist: hatchling
